bundle_app/__init__.py
bundle_app/add_packages.py
bundle_app/app_bundle.py
bundle_app/build.py
bundle_app/init.py
bundle_app/streamline.py
bundle_app/zipper.py
bundle_app/templates/AppIcon.icns
bundle_app/templates/info.jinja2
bundle_app/templates/main.py
bundle_app/templates/sdef.jinja2
bundle_app/templates/superfluous.txt
bundle_app/templates/main_ex/AppMain
bundle_app/templates/main_ex/AppMain.c
bundle_app/templates/main_ex/Makefile
bundle_app-1.0.2.dist-info/LICENSE
bundle_app-1.0.2.dist-info/METADATA
bundle_app-1.0.2.dist-info/WHEEL
bundle_app-1.0.2.dist-info/top_level.txt
bundle_app-1.0.2.dist-info/RECORD
