Metadata-Version: 2.1
Name: bundle-app
Version: 1.0.2
Summary: Constructs a macOS App bundle with a python executable.
Author-email: Marc Culler <culler@users.noreply.github.com>, "Nathan M. Dunfield" <nathan@dunfield.info>, Matthias Görner <enischte@gmail.com>
Maintainer-email: Marc Culler <culler@users.noreply.github.com>, "Nathan M. Dunfield" <nathan@dunfield.info>, Matthias Görner <enischte@gmail.com>
Project-URL: Homepage, https://github.com/3-manifolds/bundle_app
Project-URL: Bug Tracker, https://github.com/3-manifolds/bundle_app/issues
Keywords: files,metadata
Classifier: Development Status :: 3 - Alpha
Classifier: Intended Audience :: Developers
Classifier: License :: OSI Approved :: GNU General Public License v2 or later (GPLv2+)
Classifier: Operating System :: MacOS
Classifier: Programming Language :: Python
Classifier: Topic :: Desktop Environment :: File Managers
Requires-Python: >=3.10
License-File: LICENSE
Requires-Dist: toml >=0.10.0
